README.rst
setup.py
food_network_wrapper/RThumbnail.py
food_network_wrapper/Recipe.py
food_network_wrapper/__init__.py
food_network_wrapper.egg-info/PKG-INFO
food_network_wrapper.egg-info/SOURCES.txt
food_network_wrapper.egg-info/dependency_links.txt
food_network_wrapper.egg-info/requires.txt
food_network_wrapper.egg-info/top_level.txt